tuul/__init__.py
tuul/one_line_logger.py
tuul/tuul.py
tuul-0.14.1.dist-info/LICENSE
tuul-0.14.1.dist-info/METADATA
tuul-0.14.1.dist-info/WHEEL
tuul-0.14.1.dist-info/entry_points.txt
tuul-0.14.1.dist-info/top_level.txt
tuul-0.14.1.dist-info/RECORD
