Metadata-Version: 2.1
Name: tuul
Version: 0.14.1
Summary: python toolbox
Home-page: https://github.com/daniel-balosh/tuul
Author: Daniel Balosh
Author-email: no@gmail.com
License: MIT license
Keywords: tuul
Platform: UNKNOWN
Classifier: Development Status :: 2 - Pre-Alpha
Classifier: Intended Audience :: Developers
Classifier: License :: OSI Approved :: MIT License
Classifier: Natural Language :: English
Classifier: Programming Language :: Python :: 3
Classifier: Programming Language :: Python :: 3.5
Classifier: Programming Language :: Python :: 3.6
Classifier: Programming Language :: Python :: 3.7
Classifier: Programming Language :: Python :: 3.8
Requires-Python: >=3.5
